re_data/__init__.py
re_data/command_line.py
re_data/flags.py
re_data/logs.py
re_data/tracking.py
re_data/utils.py
re_data/version.py
re_data/config/__init__.py
re_data/config/system.py
re_data/config/utils.py
re_data/config/validate.py
re_data/config/yaml_utils.py
re_data/dbt_template/.gitignore
re_data/dbt_template/README.md
re_data/dbt_template/packages.yml
re_data/dbt_template/analysis/.gitkeep
re_data/dbt_template/macros/.gitkeep
re_data/dbt_template/macros/schema_changes.sql
re_data/dbt_template/models/.gitkeep
re_data/dbt_template/models/pending_orders_per_customer.sql
re_data/dbt_template/seeds/.gitkeep
re_data/dbt_template/seeds/customers.csv
re_data/dbt_template/seeds/orders.csv
re_data/dbt_template/seeds/schema.yml
re_data/dbt_template/tests/.gitkeep
re_data/include/__init__.py
re_data/include/index.html
re_data/notifications/__init__.py
re_data/notifications/email.py
re_data/notifications/slack.py
re_data/notifications/utils.py
re_data/templates/dbt_project.yml
re_data/templates/email_alert.html
re_data/templating/__init__.py
re_data/templating/render.py
re_data-0.11.0.dist-info/LICENSE
re_data-0.11.0.dist-info/METADATA
re_data-0.11.0.dist-info/WHEEL
re_data-0.11.0.dist-info/entry_points.txt
re_data-0.11.0.dist-info/top_level.txt
re_data-0.11.0.dist-info/RECORD
