Metadata-Version: 2.1
Name: re_data
Version: 0.11.0
Summary: re_data - data quality framework
Home-page: https://github.com/re-data/re-data
Author: redata-team
Author-email: mateusz@getre.io
License: MIT
Classifier: Programming Language :: Python :: 3
Classifier: License :: OSI Approved :: MIT License
Classifier: Operating System :: OS Independent
License-File: LICENSE
Requires-Dist: click <9,>=8
Requires-Dist: dbt-core <2.0.0,>=1.0.0
Requires-Dist: yachalk <0.2.0,>=0.1.0
Requires-Dist: tabulate ==0.8.9
Requires-Dist: jsonschema >=3.0.0
Requires-Dist: analytics-python
Provides-Extra: dev
Requires-Dist: isort ; extra == 'dev'
Requires-Dist: black ; extra == 'dev'
Requires-Dist: pre-commit ; extra == 'dev'
